code_mixed_text_toolkit/__init__.py
code_mixed_text_toolkit/demo.py
code_mixed_text_toolkit/data/__init__.py
code_mixed_text_toolkit/data/data.json
code_mixed_text_toolkit/data/downloader.py
code_mixed_text_toolkit/preprocessing/__init__.py
code_mixed_text_toolkit/preprocessing/frequency.py
code_mixed_text_toolkit/preprocessing/search.py
code_mixed_text_toolkit/preprocessing/tokenizer/__init__.py
code_mixed_text_toolkit/preprocessing/tokenizer/vocab.txt
code_mixed_text_toolkit-0.5.5.data/data/code_mixed_text_toolkit/data/data.json
code_mixed_text_toolkit-0.5.5.data/data/code_mixed_text_toolkit/preprocessing/tokenizer/vocab.txt
tests/__init__.py
tests/cmtt_tests.py
code_mixed_text_toolkit-0.5.5.dist-info/METADATA
code_mixed_text_toolkit-0.5.5.dist-info/WHEEL
code_mixed_text_toolkit-0.5.5.dist-info/top_level.txt
code_mixed_text_toolkit-0.5.5.dist-info/RECORD
