Metadata-Version: 2.1
Name: code-mixed-text-toolkit
Version: 0.5.5
Summary: A library for processing Code Mixed Text. Still in development!
Home-page: https://code-mixed-text-toolkit.readthedocs.io/
Author: Reuben Devanesan
Author-email: reubendevanesan@gmail.com
License: MIT
Platform: UNKNOWN
Classifier: Intended Audience :: Developers
Classifier: License :: OSI Approved :: MIT License
Classifier: Programming Language :: Python
Classifier: Programming Language :: Python :: 3
Classifier: Programming Language :: Python :: 3.9
Classifier: Programming Language :: Python :: 3.10
Classifier: Operating System :: OS Independent
Requires-Dist: numpy
Requires-Dist: pandas
Requires-Dist: requests
Requires-Dist: tqdm
